pure_visual_grounding/__init__.py
pure_visual_grounding/core.py
pure_visual_grounding/json_cleaner.py
pure_visual_grounding/prompts.py
pure_visual_grounding/utils.py
pure_visual_grounding-1.0.8.dist-info/licenses/LICENSE
pure_visual_grounding-1.0.8.dist-info/METADATA
pure_visual_grounding-1.0.8.dist-info/WHEEL
pure_visual_grounding-1.0.8.dist-info/top_level.txt
pure_visual_grounding-1.0.8.dist-info/RECORD
