Metadata-Version: 2.4
Name: pure-visual-grounding
Version: 1.0.8
Summary: A package for processing PDFs with vision-based language models
Author: Hamid Khalid
Author-email: Hamid Khalid <hamid.khalid@uni-saarland.de>
License: MIT
Classifier: Development Status :: 4 - Beta
Classifier: Intended Audience :: Developers
Classifier: Operating System :: OS Independent
Classifier: Programming Language :: Python :: 3
Classifier: Programming Language :: Python :: 3.8
Classifier: Programming Language :: Python :: 3.9
Classifier: Programming Language :: Python :: 3.10
Classifier: Programming Language :: Python :: 3.11
Requires-Python: >=3.8
License-File: LICENSE
Requires-Dist: langchain~=0.3.27
Requires-Dist: PyMuPDF
Requires-Dist: langchain-core~=0.3.72
Requires-Dist: pathlib~=1.0.1
Requires-Dist: langsmith>=0.1.17
Dynamic: author
Dynamic: license-file
Dynamic: requires-python
